times/__init__.py
times/py.typed
pytimes-1.13.0.dist-info/LICENSE
pytimes-1.13.0.dist-info/METADATA
pytimes-1.13.0.dist-info/WHEEL
pytimes-1.13.0.dist-info/RECORD
