Metadata-Version: 2.1
Name: pytimes
Version: 1.13.0
Summary: Descriptively reference time ranges in Python. `ONE_DAY` instead of `86400`.
Author: Wyko ter Haar
Author-email: wyko.ter.haar@gmail.com
Requires-Python: >=3.6,<4.0
Classifier: Programming Language :: Python :: 3
Classifier: Programming Language :: Python :: 3.6
Classifier: Programming Language :: Python :: 3.7
Classifier: Programming Language :: Python :: 3.8
Classifier: Programming Language :: Python :: 3.9
Classifier: Programming Language :: Python :: 3.10
Classifier: Programming Language :: Python :: 3.11
Classifier: Programming Language :: Python :: 3.12
